csvpath/__init__.py
csvpath/cli/__init__.py
csvpath/cli/asker.py
csvpath/cli/cli.py
csvpath/cli/const.py
csvpath/cli/debug_config.py
csvpath/cli/drill_down.py
csvpath/cli/function_describer.py
csvpath/cli/function_lister.py
csvpath/cli/selecter.py
csvpath/csvpath.py
csvpath/csvpaths.py
csvpath/managers/__init__.py
csvpath/managers/errors/error.py
csvpath/managers/errors/error_collector.py
csvpath/managers/errors/error_comms.py
csvpath/managers/errors/error_manager.py
csvpath/managers/files/file_manager.py
csvpath/managers/files/file_metadata.py
csvpath/managers/files/file_registrar.py
csvpath/managers/files/files_listener.py
csvpath/managers/files/lines_and_headers_cacher.py
csvpath/managers/integrations/ckan/ckan.py
csvpath/managers/integrations/ckan/ckan_listener.py
csvpath/managers/integrations/ckan/datafile.py
csvpath/managers/integrations/ckan/dataset.py
csvpath/managers/integrations/ol/event.py
csvpath/managers/integrations/ol/event_result.py
csvpath/managers/integrations/ol/file_listener_ol.py
csvpath/managers/integrations/ol/job.py
csvpath/managers/integrations/ol/ol_listener.py
csvpath/managers/integrations/ol/paths_listener_ol.py
csvpath/managers/integrations/ol/result_listener_ol.py
csvpath/managers/integrations/ol/results_listener_ol.py
csvpath/managers/integrations/ol/run.py
csvpath/managers/integrations/ol/run_listener_ol.py
csvpath/managers/integrations/ol/run_state.py
csvpath/managers/integrations/ol/sender.py
csvpath/managers/integrations/otlp/error_metrics.py
csvpath/managers/integrations/otlp/metrics.py
csvpath/managers/integrations/otlp/otlp_error_listener.py
csvpath/managers/integrations/otlp/otlp_file_listener.py
csvpath/managers/integrations/otlp/otlp_listener.py
csvpath/managers/integrations/otlp/otlp_paths_listener.py
csvpath/managers/integrations/otlp/otlp_result_listener.py
csvpath/managers/integrations/otlp/otlp_results_listener.py
csvpath/managers/integrations/scripts/scripts_results_listener.py
csvpath-0.0.591.dist-info/LICENSE
csvpath-0.0.591.dist-info/METADATA
csvpath-0.0.591.dist-info/WHEEL
csvpath-0.0.591.dist-info/entry_points.txt
csvpath-0.0.591.dist-info/RECORD
