Metadata-Version: 2.3
Name: csvpath
Version: 0.0.591
Summary: A data preboarding framework for ingesting, managing, and validating CSV, Excel, and other tabular data files using a Collect, Store, Validate, Publish architecture to create a trusted publisher for downstream data consumers.
Author: David Kershaw
Author-email: info@csvpath.org
Requires-Python: >3.10,<4.0
Classifier: Development Status :: 3 - Alpha
Classifier: Environment :: Console
Classifier: Intended Audience :: Developers
Classifier: Programming Language :: Python
Classifier: Programming Language :: Python :: 3
Classifier: Programming Language :: Python :: 3.11
Classifier: Programming Language :: Python :: 3.12
Classifier: Programming Language :: Python :: 3.13
Classifier: Topic :: File Formats
Classifier: Topic :: Office/Business :: Financial :: Spreadsheet
Classifier: Topic :: Software Development :: Libraries :: Python Modules
Classifier: Topic :: Software Development :: Quality Assurance
Classifier: Topic :: Software Development :: Testing
Classifier: Topic :: Text Processing
Classifier: Topic :: Utilities
Provides-Extra: pandas
Requires-Dist: azure-storage-blob (>=12.24.1,<13.0.0)
Requires-Dist: boto3 (>=1.35.91,<2.0.0)
Requires-Dist: ckanapi (>=4.8,<5.0)
Requires-Dist: email-validator (>=2.2.0,<3.0.0)
Requires-Dist: google-cloud-storage (>=3.1.0,<4.0.0)
Requires-Dist: inflect (>=7.4.0,<8.0.0)
Requires-Dist: jinja2 (>=3.1.6,<4.0.0)
Requires-Dist: jsonlines (>=4.0.0,<5.0.0)
Requires-Dist: jsonpath-ng (>=1.7.0,<2.0.0)
Requires-Dist: lark (>=1.2.2,<2.0.0)
Requires-Dist: lxml (>=6.0.2,<7.0.0)
Requires-Dist: marquez-python (>=0.50.0,<0.51.0)
Requires-Dist: metaphone (>=0.6,<0.7)
Requires-Dist: mysqlclient (>=2.2.7,<3.0.0)
Requires-Dist: openlineage-python (>=1.25.0,<2.0.0)
Requires-Dist: opentelemetry-distro[otlp] (>=0.50b0,<0.51)
Requires-Dist: pandas (>=2.2.2,<3.0.0) ; extra == "pandas"
Requires-Dist: paramiko (>=3.5.0,<4.0.0)
Requires-Dist: pdoc (>=15.0.1,<16.0.0)
Requires-Dist: prompt-toolkit (>=3.0.50,<4.0.0)
Requires-Dist: psycopg2-binary (>=2.9.10,<3.0.0)
Requires-Dist: pyjson5 (>=2.0.0,<3.0.0)
Requires-Dist: pylightxl (>=1.61,<2.0)
Requires-Dist: pytest (>=8.3.3,<9.0.0)
Requires-Dist: python-dateutil (>=2.9.0.post0,<3.0.0)
Requires-Dist: pytz (>=2024.2,<2025.0)
Requires-Dist: requests (>=2.32.3,<3.0.0)
Requires-Dist: smart-open[all] (>=7.1.0,<8.0.0)
Requires-Dist: sqlalchemy (>=2.0.38,<3.0.0)
Requires-Dist: tabulate (>=0.9.0,<0.10.0)
Requires-Dist: validators (>=0.34.0,<0.35.0)
Project-URL: Csvpath.org, https://www.csvpath.org
Project-URL: Github, https://github.com/csvpath/csvpath.git
